{
	"Commandement Patrouilleur": {
		"liste_militaire": "1",
		"type_orga": "6",
		"Patrouilleur naval PN-1": {
			"liste_militaire": "2",
			"type_orga": "7",
			"materiel": {
				"Patrouilleur naval": "1"
			},
			"Ilôt": {
				"liste_militaire": "1",
				"type_orga": "8",
				"Poste de Commandement": { "liste_militaire": "10", "type_orga": "9" },
				"Radar": { "liste_militaire": "8", "type_orga": "9" },
				"Propulsion et Systèmes Vitaux": { "liste_militaire": "8", "type_orga": "9" }
			},
			"Vie et ressources": {
				"liste_militaire": "1",
				"type_orga": "8",
				"Maintenance": { "liste_militaire": "10", "type_orga": "9" },
				"Compagnie médicale": { "liste_militaire": "4", "type_orga": "9" },
				"Cuisine": { "liste_militaire": "8", "type_orga": "9" }
			},
			"Sécurité, hangar et pont d'envol": {
				"liste_militaire": "1",
				"type_orga": "8",
				"Armement": { "liste_militaire": "6", "type_orga": "9" },
				"Sécurité": { "liste_militaire": "20", "type_orga": "9" },
				"Pompiers": { "liste_militaire": "20", "type_orga": "9" },
				"Ravitaillement": { "liste_militaire": "5", "type_orga": "9" },
				"Pont d'envol": { "liste_militaire": "6", "type_orga": "9" }
			},
			"Hélicoptère Multi-Fonctions": {
				"liste_militaire": "8",
				"type_orga": "8",
				"materiel": {
					"Hélicoptère Multi-Fonctions": "1"
				}
			}
		},
		"Patrouilleur naval PN-2": {
			"liste_militaire": "2",
			"type_orga": "7",
			"materiel": {
				"Patrouilleur naval": "1"
			},
			"Ilôt": {
				"liste_militaire": "1",
				"type_orga": "8",
				"Poste de Commandement": { "liste_militaire": "10", "type_orga": "9" },
				"Radar": { "liste_militaire": "8", "type_orga": "9" },
				"Propulsion et Systèmes Vitaux": { "liste_militaire": "8", "type_orga": "9" }
			},
			"Vie et ressources": {
				"liste_militaire": "1",
				"type_orga": "8",
				"Maintenance": { "liste_militaire": "10", "type_orga": "9" },
				"Compagnie médicale": { "liste_militaire": "4", "type_orga": "9" },
				"Cuisine": { "liste_militaire": "8", "type_orga": "9" }
			},
			"Sécurité, hangar et pont d'envol": {
				"liste_militaire": "1",
				"type_orga": "8",
				"Armement": { "liste_militaire": "6", "type_orga": "9" },
				"Sécurité": { "liste_militaire": "20", "type_orga": "9" },
				"Pompiers": { "liste_militaire": "20", "type_orga": "9" },
				"Ravitaillement": { "liste_militaire": "5", "type_orga": "9" },
				"Pont d'envol": { "liste_militaire": "6", "type_orga": "9" }
			},
			"Hélicoptère Multi-Fonctions": {
				"liste_militaire": "8",
				"type_orga": "8",
				"materiel": {
					"Hélicoptère Multi-Fonctions": "1"
				}
			}
		},
		"Patrouilleur naval PN-3": {
			"liste_militaire": "2",
			"type_orga": "7",
			"materiel": {
				"Patrouilleur naval": "1"
			},
			"Ilôt": {
				"liste_militaire": "1",
				"type_orga": "8",
				"Poste de Commandement": { "liste_militaire": "10", "type_orga": "9" },
				"Radar": { "liste_militaire": "8", "type_orga": "9" },
				"Propulsion et Systèmes Vitaux": { "liste_militaire": "8", "type_orga": "9" }
			},
			"Vie et ressources": {
				"liste_militaire": "1",
				"type_orga": "8",
				"Maintenance": { "liste_militaire": "10", "type_orga": "9" },
				"Compagnie médicale": { "liste_militaire": "4", "type_orga": "9" },
				"Cuisine": { "liste_militaire": "8", "type_orga": "9" }
			},
			"Sécurité, hangar et pont d'envol": {
				"liste_militaire": "1",
				"type_orga": "8",
				"Armement": { "liste_militaire": "6", "type_orga": "9" },
				"Sécurité": { "liste_militaire": "20", "type_orga": "9" },
				"Pompiers": { "liste_militaire": "20", "type_orga": "9" },
				"Ravitaillement": { "liste_militaire": "5", "type_orga": "9" },
				"Pont d'envol": { "liste_militaire": "6", "type_orga": "9" }
			},
			"Hélicoptère Multi-Fonctions": {
				"liste_militaire": "8",
				"type_orga": "8",
				"materiel": {
					"Hélicoptère Multi-Fonctions": "1"
				}
			}
		}
	},
	"Commandement de Remorquage en Haute Mer": {
		"liste_militaire": "1",
		"type_orga": "6",
		"Remorqueur de Haute Mer RHM-1": {
			"liste_militaire": "2",
			"type_orga": "7",
			"materiel": {
				"Remorqueur de haute mer": "1"
			},
			"Ilôt": {
				"liste_militaire": "1",
				"type_orga": "8",
				"Poste de Commandement": { "liste_militaire": "10", "type_orga": "9" },
				"Propulsion et Systèmes Vitaux": { "liste_militaire": "8", "type_orga": "9" }
			},
			"Vie et ressources": {
				"liste_militaire": "1",
				"type_orga": "8",
				"Maintenance": { "liste_militaire": "10", "type_orga": "9" },
				"Compagnie médicale": { "liste_militaire": "4", "type_orga": "9" },
				"Cuisine": { "liste_militaire": "8", "type_orga": "9" }
			},
			"Sécurité, hangar et pont d'envol": {
				"liste_militaire": "1",
				"type_orga": "8",
				"Sécurité": { "liste_militaire": "12", "type_orga": "9" },
				"Pompiers": { "liste_militaire": "20", "type_orga": "9" },
				"Ravitaillement": { "liste_militaire": "5", "type_orga": "9" }
			}
		},
		"Remorqueur de Haute Mer RHM-2": {
			"liste_militaire": "2",
			"type_orga": "7",
			"materiel": {
				"Remorqueur de haute mer": "1"
			},
			"Ilôt": {
				"liste_militaire": "1",
				"type_orga": "8",
				"Poste de Commandement": { "liste_militaire": "10", "type_orga": "9" },
				"Propulsion et Systèmes Vitaux": { "liste_militaire": "8", "type_orga": "9" }
			},
			"Vie et ressources": {
				"liste_militaire": "1",
				"type_orga": "8",
				"Maintenance": { "liste_militaire": "10", "type_orga": "9" },
				"Compagnie médicale": { "liste_militaire": "4", "type_orga": "9" },
				"Cuisine": { "liste_militaire": "8", "type_orga": "9" }
			},
			"Sécurité, hangar et pont d'envol": {
				"liste_militaire": "1",
				"type_orga": "8",
				"Sécurité": { "liste_militaire": "12", "type_orga": "9" },
				"Pompiers": { "liste_militaire": "20", "type_orga": "9" },
				"Ravitaillement": { "liste_militaire": "5", "type_orga": "9" }
			}
		},
		"Remorqueur de Haute Mer RHM-3": {
			"liste_militaire": "2",
			"type_orga": "7",
			"materiel": {
				"Remorqueur de haute mer": "1"
			},
			"Ilôt": {
				"liste_militaire": "1",
				"type_orga": "8",
				"Poste de Commandement": { "liste_militaire": "10", "type_orga": "9" },
				"Propulsion et Systèmes Vitaux": { "liste_militaire": "8", "type_orga": "9" }
			},
			"Vie et ressources": {
				"liste_militaire": "1",
				"type_orga": "8",
				"Maintenance": { "liste_militaire": "10", "type_orga": "9" },
				"Compagnie médicale": { "liste_militaire": "4", "type_orga": "9" },
				"Cuisine": { "liste_militaire": "8", "type_orga": "9" }
			},
			"Sécurité, hangar et pont d'envol": {
				"liste_militaire": "1",
				"type_orga": "8",
				"Sécurité": { "liste_militaire": "12", "type_orga": "9" },
				"Pompiers": { "liste_militaire": "20", "type_orga": "9" },
				"Ravitaillement": { "liste_militaire": "5", "type_orga": "9" }
			}
		},
		"Remorqueur de Haute Mer RHM-4": {
			"liste_militaire": "2",
			"type_orga": "7",
			"materiel": {
				"Remorqueur de haute mer": "1"
			},
			"Ilôt": {
				"liste_militaire": "1",
				"type_orga": "8",
				"Poste de Commandement": { "liste_militaire": "10", "type_orga": "9" },
				"Propulsion et Systèmes Vitaux": { "liste_militaire": "8", "type_orga": "9" }
			},
			"Vie et ressources": {
				"liste_militaire": "1",
				"type_orga": "8",
				"Maintenance": { "liste_militaire": "10", "type_orga": "9" },
				"Compagnie médicale": { "liste_militaire": "4", "type_orga": "9" },
				"Cuisine": { "liste_militaire": "8", "type_orga": "9" }
			},
			"Sécurité, hangar et pont d'envol": {
				"liste_militaire": "1",
				"type_orga": "8",
				"Sécurité": { "liste_militaire": "12", "type_orga": "9" },
				"Pompiers": { "liste_militaire": "20", "type_orga": "9" },
				"Ravitaillement": { "liste_militaire": "5", "type_orga": "9" }
			}
		},
		"Remorqueur de Haute Mer RHM-5": {
			"liste_militaire": "2",
			"type_orga": "7",
			"materiel": {
				"Remorqueur de haute mer": "1"
			},
			"Ilôt": {
				"liste_militaire": "1",
				"type_orga": "8",
				"Poste de Commandement": { "liste_militaire": "10", "type_orga": "9" },
				"Propulsion et Systèmes Vitaux": { "liste_militaire": "8", "type_orga": "9" }
			},
			"Vie et ressources": {
				"liste_militaire": "1",
				"type_orga": "8",
				"Maintenance": { "liste_militaire": "10", "type_orga": "9" },
				"Compagnie médicale": { "liste_militaire": "4", "type_orga": "9" },
				"Cuisine": { "liste_militaire": "8", "type_orga": "9" }
			},
			"Sécurité, hangar et pont d'envol": {
				"liste_militaire": "1",
				"type_orga": "8",
				"Sécurité": { "liste_militaire": "12", "type_orga": "9" },
				"Pompiers": { "liste_militaire": "20", "type_orga": "9" },
				"Ravitaillement": { "liste_militaire": "5", "type_orga": "9" }
			}
		}
	},
	"Commandement de Dépollution Maritime": {
		"liste_militaire": "1",
		"type_orga": "6",
		"Bâtiment de Dépollution Maritime BDM-1": {
			"liste_militaire": "1",
			"type_orga": "7",
			"materiel": {
				"Bâtiment de Dépollution Maritime": "1"
			},
			"Ilôt": {
				"liste_militaire": "1",
				"type_orga": "8",
				"Poste de Commandement": { "liste_militaire": "10", "type_orga": "9" },
				"Propulsion et Systèmes Vitaux": { "liste_militaire": "12", "type_orga": "9" }
			},
			"Vie et ressources": {
				"liste_militaire": "1",
				"type_orga": "8",
				"Maintenance": { "liste_militaire": "10", "type_orga": "9" },
				"Compagnie médicale": { "liste_militaire": "4", "type_orga": "9" },
				"Cuisine": { "liste_militaire": "8", "type_orga": "9" }
			},
			"Sécurité, hangar et pont d'envol": {
				"liste_militaire": "1",
				"type_orga": "8",
				"Sécurité": { "liste_militaire": "20", "type_orga": "9" },
				"Pompiers": { "liste_militaire": "16", "type_orga": "9" },
				"Ravitaillement": { "liste_militaire": "5", "type_orga": "5" }
			}
		},
		"Bâtiment de Dépollution Maritime BDM-2": {
			"liste_militaire": "1",
			"type_orga": "7",
			"materiel": {
				"Bâtiment de Dépollution Maritime": "1"
			},
			"Ilôt": {
				"liste_militaire": "1",
				"type_orga": "8",
				"Poste de Commandement": { "liste_militaire": "10", "type_orga": "9" },
				"Propulsion et Systèmes Vitaux": { "liste_militaire": "12", "type_orga": "9" }
			},
			"Vie et ressources": {
				"liste_militaire": "1",
				"type_orga": "8",
				"Maintenance": { "liste_militaire": "10", "type_orga": "9" },
				"Compagnie médicale": { "liste_militaire": "4", "type_orga": "9" },
				"Cuisine": { "liste_militaire": "8", "type_orga": "9" }
			},
			"Sécurité, hangar et pont d'envol": {
				"liste_militaire": "1",
				"type_orga": "8",
				"Sécurité": { "liste_militaire": "20", "type_orga": "9" },
				"Pompiers": { "liste_militaire": "16", "type_orga": "9" },
				"Ravitaillement": { "liste_militaire": "5", "type_orga": "5" }
			}
		}
	},
	"Commandement de Vedette": {
		"liste_militaire": "1",
		"type_orga": "6",
		"Vedette Légère VL-1": {
			"liste_militaire": "7",
			"type_orga": "7",
			"materiel": {
				"Vedette légère": "1"
			}
		},
		"Vedette Légère VL-2": {
			"liste_militaire": "7",
			"type_orga": "7",
			"materiel": {
				"Vedette légère": "1"
			}
		},
		"Vedette Légère VL-3": {
			"liste_militaire": "7",
			"type_orga": "7",
			"materiel": {
				"Vedette légère": "1"
			}
		},
		"Vedette Légère VL-4": {
			"liste_militaire": "7",
			"type_orga": "7",
			"materiel": {
				"Vedette légère": "1"
			}
		},
		"Vedette Légère VL-5": {
			"liste_militaire": "7",
			"type_orga": "7",
			"materiel": {
				"Vedette légère": "1"
			}
		},
		"Vedette Légère VL-6": {
			"liste_militaire": "7",
			"type_orga": "7",
			"materiel": {
				"Vedette légère": "1"
			}
		},
		"Vedette Légère VL-7": {
			"liste_militaire": "7",
			"type_orga": "7",
			"materiel": {
				"Vedette légère": "1"
			}
		},
		"Vedette Légère VL-8": {
			"liste_militaire": "7",
			"type_orga": "7",
			"materiel": {
				"Vedette légère": "1"
			}
		},
		"Vedette Légère VL-9": {
			"liste_militaire": "7",
			"type_orga": "7",
			"materiel": {
				"Vedette légère": "1"
			}
		},
		"Vedette Légère VL-10": {
			"liste_militaire": "7",
			"type_orga": "7",
			"materiel": {
				"Vedette légère": "1"
			}
		}
	},
	"Commandement aérien": {
		"liste_militaire": "1",
		"type_orga": "6",
		"Groupe APD": {
			"liste_militaire": "1",
			"type_orga": "7",
			"Avion de Patrouille et de Détection APD-1": {
				"liste_militaire": "18",
				"type_orga": "8",
				"materiel": {
					"Avion de Patrouille et de Détection": "1"
				}
			},
			"Avion de Patrouille et de Détection APD-2": {
				"liste_militaire": "18",
				"type_orga": "8",
				"materiel": {
					"Avion de Patrouille et de Détection": "1"
				}
			}
		},
		"Groupe HMF": {
			"liste_militaire": "1",
			"type_orga": "7",
			"Hélicoptère Multi-Fonctions HMF-1": {
				"liste_militaire": "8",
				"type_orga": "8",
				"materiel": {
					"Hélicoptère Multi-Fonctions": "1"
				}
			},
			"Hélicoptère Multi-Fonctions HMF-2": {
				"liste_militaire": "8",
				"type_orga": "8",
				"materiel": {
					"Hélicoptère Multi-Fonctions": "1"
				}
			},
			"Hélicoptère Multi-Fonctions HMF-3": {
				"liste_militaire": "8",
				"type_orga": "8",
				"materiel": {
					"Hélicoptère Multi-Fonctions": "1"
				}
			},
			"Hélicoptère Multi-Fonctions HMF-4": {
				"liste_militaire": "8",
				"type_orga": "8",
				"materiel": {
					"Hélicoptère Multi-Fonctions": "1"
				}
			},
			"Hélicoptère Multi-Fonctions HMF-5": {
				"liste_militaire": "8",
				"type_orga": "8",
				"materiel": {
					"Hélicoptère Multi-Fonctions": "1"
				}
			},
			"Hélicoptère Multi-Fonctions HMF-6": {
				"liste_militaire": "8",
				"type_orga": "8",
				"materiel": {
					"Hélicoptère Multi-Fonctions": "1"
				}
			},
			"Hélicoptère Multi-Fonctions HMF-7": {
				"liste_militaire": "8",
				"type_orga": "8",
				"materiel": {
					"Hélicoptère Multi-Fonctions": "1"
				}
			},
			"Hélicoptère Multi-Fonctions HMF-8": {
				"liste_militaire": "8",
				"type_orga": "8",
				"materiel": {
					"Hélicoptère Multi-Fonctions": "1"
				}
			},
			"Hélicoptère Multi-Fonctions HMF-9": {
				"liste_militaire": "8",
				"type_orga": "8",
				"materiel": {
					"Hélicoptère Multi-Fonctions": "1"
				}
			},
			"Hélicoptère Multi-Fonctions HMF-10": {
				"liste_militaire": "8",
				"type_orga": "8",
				"materiel": {
					"Hélicoptère Multi-Fonctions": "1"
				}
			}
		},
		"Groupe ATTP": {
			"liste_militaire": "1",
			"type_orga": "7",
			"Avion de Transport à Turbo-Propulseurs ATTP-1": {
				"liste_militaire": "11",
				"type_orga": "8",
				"materiel": {
					"Avion de Transport à Turbo-Propulseurs": "1"
				}
			},
			"Avion de Transport à Turbo-Propulseurs ATTP-2": {
				"liste_militaire": "11",
				"type_orga": "8",
				"materiel": {
					"Avion de Transport à Turbo-Propulseurs": "1"
				}
			}
		}
	}
}